fdfs_client/__init__.py
fdfs_client/client.py
fdfs_client/connection.py
fdfs_client/exceptions.py
fdfs_client/fdfs_protol.py
fdfs_client/fdfs_test.py
fdfs_client/storage_client.py
fdfs_client/tracker_client.py
fdfs_client/utils.py
easyPyFdfs-3.0.1.dist-info/LICENSE
easyPyFdfs-3.0.1.dist-info/METADATA
easyPyFdfs-3.0.1.dist-info/WHEEL
easyPyFdfs-3.0.1.dist-info/top_level.txt
easyPyFdfs-3.0.1.dist-info/RECORD
