Metadata-Version: 2.1
Name: easyPyFdfs
Version: 3.0.1
Summary: Python3 and Python2 client for Fastdfs
Home-page: http://github.com/renoyuan/easyPyFdfs
Author: renoyuan
Author-email: renoyuan@foxmail.com
License: GPLV3
Keywords: Fastdfs,Distribute File System
License-File: LICENSE
